AwkChengxushejiYuyan/README.md
AwkChengxushejiYuyan/__init__.py
AwkChengxushejiYuyan/__main__.py
AwkChengxushejiYuyan/file.epub
AwkChengxushejiYuyan/index.html
AwkChengxushejiYuyan/css/__init__.py
AwkChengxushejiYuyan/css/annotations.css
AwkChengxushejiYuyan/css/main.css
AwkChengxushejiYuyan/css/normalize.css
AwkChengxushejiYuyan/css/popup.css
AwkChengxushejiYuyan/font/__init__.py
AwkChengxushejiYuyan/font/fontello.eot
AwkChengxushejiYuyan/font/fontello.svg
AwkChengxushejiYuyan/font/fontello.ttf
AwkChengxushejiYuyan/font/fontello.woff
AwkChengxushejiYuyan/img/__init__.py
AwkChengxushejiYuyan/img/annotator-glyph-sprite.png
AwkChengxushejiYuyan/img/annotator-icon-sprite.png
AwkChengxushejiYuyan/img/apple-touch-icon.png
AwkChengxushejiYuyan/img/cancelfullscreen.png
AwkChengxushejiYuyan/img/close.png
AwkChengxushejiYuyan/img/fullscreen.png
AwkChengxushejiYuyan/img/loader.gif
AwkChengxushejiYuyan/img/menu-icon.png
AwkChengxushejiYuyan/img/save.png
AwkChengxushejiYuyan/img/saved.png
AwkChengxushejiYuyan/img/settings-s.png
AwkChengxushejiYuyan/img/settings.png
AwkChengxushejiYuyan/img/star.png
AwkChengxushejiYuyan/js/__init__.py
AwkChengxushejiYuyan/js/epub.js
AwkChengxushejiYuyan/js/epub.min.js
AwkChengxushejiYuyan/js/epub.min.map
AwkChengxushejiYuyan/js/hooks.min.js
AwkChengxushejiYuyan/js/hooks.min.map
AwkChengxushejiYuyan/js/reader.js
AwkChengxushejiYuyan/js/reader.js.map
AwkChengxushejiYuyan/js/reader.min.js
AwkChengxushejiYuyan/js/reader.min.map
AwkChengxushejiYuyan/js/hooks/__init__.py
AwkChengxushejiYuyan/js/hooks/extensions/__init__.py
AwkChengxushejiYuyan/js/hooks/extensions/highlight.js
AwkChengxushejiYuyan/js/libs/__init__.py
AwkChengxushejiYuyan/js/libs/jquery.min.js
AwkChengxushejiYuyan/js/libs/localforage.min.js
AwkChengxushejiYuyan/js/libs/screenfull.js
AwkChengxushejiYuyan/js/libs/screenfull.min.js
AwkChengxushejiYuyan/js/libs/zip.min.js
AwkChengxushejiYuyan/js/plugins/__init__.py
AwkChengxushejiYuyan/js/plugins/hypothesis.js
awk_chengxusheji_yuyan-2024.3.1.0.dist-info/METADATA
awk_chengxusheji_yuyan-2024.3.1.0.dist-info/WHEEL
awk_chengxusheji_yuyan-2024.3.1.0.dist-info/entry_points.txt
awk_chengxusheji_yuyan-2024.3.1.0.dist-info/top_level.txt
awk_chengxusheji_yuyan-2024.3.1.0.dist-info/RECORD
